{
  "team": "Australia",
  "slug": "australia",
  "stats": {
    "total_breaks": 2,
    "gained": 1,
    "lost": 1,
    "mean_delta": 0.05,
    "verdict": "neutral",
    "pressing_n": 1,
    "pressing_mean": -0.1,
    "pressing_kept": 0,
    "nonpressing_n": 1,
    "nonpressing_mean": 0.2,
    "nonpressing_gained": 1,
    "half1_mean": -0.1,
    "half2_mean": 0.2
  },
  "breaks": [
    {
      "opponent": "T\u00fcrkiye",
      "half": 1,
      "match_label": "Australia v T\u00fcrkiye",
      "pre_rate": 0.2,
      "post_rate": 0.1,
      "delta": -0.1,
      "pressing": true
    },
    {
      "opponent": "T\u00fcrkiye",
      "half": 2,
      "match_label": "Australia v T\u00fcrkiye",
      "pre_rate": 0.0,
      "post_rate": 0.2,
      "delta": 0.2,
      "pressing": false
    }
  ],
  "insight": "For the Australian team in the 2026 World Cup, hydration breaks have had a notable impact on their performance. On average, they tend to gain momentum after a break, with a slight increase in their scoring rate, as indicated by the mean change of +0.050 per minute across the two breaks. However, the numbers also suggest that when Australia is pressing before a hydration break, they tend to lose momentum, with their scoring rate decreasing by an average of 0.100 per minute, and they were unable to maintain their momentum after the break in the one instance this occurred. In contrast, when they are not pressing before a break, they experience a more significant increase in their scoring rate, averaging a gain of 0.200 per minute, which could be a strategic consideration for their coaches."
}